{
  "appPageId" : "ea65f671-57c8-4a3c-b624-642f6fe5b11a",
  "componentName" : "siteforce:sldsOneColLayout",
  "id" : "39ea78c2-878a-44b1-8328-2b8386819d22",
  "label" : "User Settings",
  "regions" : [ {
    "id" : "83763a01-850b-4538-b842-871a614e8e81",
    "regionName" : "header",
    "type" : "region"
  }, {
    "components" : [ {
      "componentAttributes" : {
        "accountSectionTitle" : "Account",
        "accountTabName" : "Account Details",
        "connectedSourcesTabName" : "Connected Sources",
        "emailNotificationsTitle" : "Email Notifications",
        "emailSectionDescText" : "When email notifications are enabled, email me when someone:",
        "hideChatterNotificationSettings" : true,
        "hideConnectedSources" : false,
        "hideEmailNotificationSettings" : false,
        "hideProfileVisibilitySettings" : true,
        "id" : "{!recordId}",
        "locationTitle" : "Location",
        "profileSectionDescText" : "Customize who is able to see what on your profile page",
        "profileSectionToolTipText" : "Restricted: Visible to the employees of the company that created the site. Members: Visible to logged-in members. Public: Visible to anyone viewing pages that don't require login.",
        "profileVisibilityTitle" : "Profile Visibility",
        "settingsPageTitle" : "My Settings"
      },
      "componentName" : "forceCommunity:userSettingsCustomizable",
      "id" : "3fff9056-6eb4-4a5d-b3d1-d1e684370e59",
      "renderPriority" : "NEUTRAL",
      "renditionMap" : { },
      "type" : "component"
    } ],
    "id" : "1bd1de61-9911-40fb-81d2-8f9f29d19405",
    "regionName" : "content",
    "type" : "region"
  }, {
    "id" : "7a37d305-b441-4310-847b-89de0a0821d4",
    "regionName" : "footer",
    "type" : "region"
  } ],
  "themeLayoutType" : "Inner",
  "type" : "view",
  "viewType" : "usersettings"
}